napari_points2regions/__init__.py
napari_points2regions/_version.py
napari_points2regions/_widget.py
napari_points2regions/napari.yaml
napari_points2regions/_tests/__init__.py
napari_points2regions/_tests/test_widget.py
napari_points2regions-0.0.2.dist-info/LICENSE
napari_points2regions-0.0.2.dist-info/METADATA
napari_points2regions-0.0.2.dist-info/WHEEL
napari_points2regions-0.0.2.dist-info/entry_points.txt
napari_points2regions-0.0.2.dist-info/top_level.txt
napari_points2regions-0.0.2.dist-info/RECORD
