Metadata-Version: 2.1
Name: napari-points2regions
Version: 0.0.2
Summary: A napari plugin for Points2Regions
Home-page: https://github.com/wahlby-lab/napari-points2regions
Author: Jonas Windhager
Author-email: jonas@windhager.io
License: MIT
Project-URL: Bug Tracker, https://github.com/wahlby-lab/napari-points2regions/issues
Project-URL: Documentation, https://github.com/wahlby-lab/napari-points2regions#README.md
Project-URL: Source Code, https://github.com/wahlby-lab/napari-points2regions
Project-URL: User Support, https://github.com/wahlby-lab/napari-points2regions/issues
Classifier: Framework :: napari
Classifier: Intended Audience :: Science/Research
Classifier: License :: OSI Approved :: MIT License
Classifier: Operating System :: OS Independent
Classifier: Programming Language :: Python
Classifier: Programming Language :: Python :: 3
Classifier: Programming Language :: Python :: 3 :: Only
Classifier: Programming Language :: Python :: 3.9
Classifier: Programming Language :: Python :: 3.10
Classifier: Programming Language :: Python :: 3.11
Classifier: Topic :: Scientific/Engineering :: Image Processing
Requires-Python: >=3.9
License-File: LICENSE
Requires-Dist: colorcet
Requires-Dist: magicgui
Requires-Dist: napari
Requires-Dist: numpy
Requires-Dist: pandas
Requires-Dist: points2regions >=0.0.4
Provides-Extra: testing
Requires-Dist: tox ; extra == 'testing'
Requires-Dist: pytest ; extra == 'testing'
Requires-Dist: pytest-cov ; extra == 'testing'
Requires-Dist: pytest-qt ; extra == 'testing'
Requires-Dist: napari ; extra == 'testing'
Requires-Dist: pyqt5 ; extra == 'testing'
